README.md
setup.py
runpod_pulumi_infra/__init__.py
runpod_pulumi_infra/_inputs.py
runpod_pulumi_infra/_utilities.py
runpod_pulumi_infra/network_storage.py
runpod_pulumi_infra/outputs.py
runpod_pulumi_infra/pod.py
runpod_pulumi_infra/provider.py
runpod_pulumi_infra/pulumi-plugin.json
runpod_pulumi_infra/py.typed
runpod_pulumi_infra.egg-info/PKG-INFO
runpod_pulumi_infra.egg-info/SOURCES.txt
runpod_pulumi_infra.egg-info/dependency_links.txt
runpod_pulumi_infra.egg-info/not-zip-safe
runpod_pulumi_infra.egg-info/requires.txt
runpod_pulumi_infra.egg-info/top_level.txt
runpod_pulumi_infra/config/__init__.py
runpod_pulumi_infra/config/vars.py